{
  "language": "zh-TW",
  "country": "TW",
  "type": "names",
  "version": "2.0.0",
  "items": [
    {"value": "美", "weight": 2.0, "tags": ["beautiful"], "era": "classic", "meaning": "beautiful"},
    {"value": "雅", "weight": 1.9, "tags": ["elegant", "refined"], "era": "modern", "meaning": "elegant, refined"},
    {"value": "婷", "weight": 1.8, "tags": ["graceful", "elegant"], "era": "modern", "meaning": "graceful, elegant"},
    {"value": "怡", "weight": 1.7, "tags": ["pleasant", "happy"], "era": "modern", "meaning": "pleasant, happy"},
    {"value": "玲", "weight": 1.6, "tags": ["elegant", "delicate"], "era": "modern", "meaning": "elegant, delicate"},
    {"value": "慧", "weight": 1.5, "tags": ["wise", "intelligent"], "era": "classic", "meaning": "wise, intelligent"},
    {"value": "君", "weight": 1.4, "tags": ["noble", "ruler"], "era": "classic", "meaning": "noble, ruler"},
    {"value": "秀", "weight": 1.3, "tags": ["elegant", "beautiful"], "era": "traditional", "meaning": "elegant, beautiful"},
    {"value": "芳", "weight": 1.2, "tags": ["fragrant", "virtue"], "era": "classic", "meaning": "fragrant, virtue"},
    {"value": "珮", "weight": 1.1, "tags": ["precious", "jade"], "era": "traditional", "meaning": "precious jade ornament"},
    {"value": "琳", "weight": 1.0, "tags": ["precious", "jade"], "era": "modern", "meaning": "precious jade"},
    {"value": "儀", "weight": 1.0, "tags": ["ceremony", "graceful"], "era": "classic", "meaning": "ceremony, graceful"},
    {"value": "瑩", "weight": 1.0, "tags": ["crystal", "bright"], "era": "modern", "meaning": "crystal, bright"},
    {"value": "靜", "weight": 0.9, "tags": ["peaceful", "quiet"], "era": "classic", "meaning": "peaceful, quiet"},
    {"value": "敏", "weight": 0.9, "tags": ["smart", "agile"], "era": "classic", "meaning": "smart, agile"},
    {"value": "倩", "weight": 0.9, "tags": ["beautiful", "charming"], "era": "classic", "meaning": "beautiful, charming"},
    {"value": "淑", "weight": 0.8, "tags": ["gentle", "virtuous"], "era": "traditional", "meaning": "gentle, virtuous"},
    {"value": "菁", "weight": 0.8, "tags": ["essence", "elite"], "era": "modern", "meaning": "essence, elite"},
    {"value": "麗", "weight": 0.8, "tags": ["beautiful"], "era": "classic", "meaning": "beautiful"},
    {"value": "霞", "weight": 0.7, "tags": ["nature", "sunset"], "era": "classic", "meaning": "rosy cloud"},
    {"value": "萍", "weight": 0.7, "tags": ["nature", "water"], "era": "classic", "meaning": "duckweed"},
    {"value": "華", "weight": 0.7, "tags": ["magnificent", "china"], "era": "classic", "meaning": "magnificent, China"},
    {"value": "惠", "weight": 0.6, "tags": ["kind", "benevolent"], "era": "classic", "meaning": "kind, benevolent"},
    {"value": "珊", "weight": 0.6, "tags": ["coral", "precious"], "era": "modern", "meaning": "coral"},
    {"value": "欣", "weight": 0.6, "tags": ["happy", "joyful"], "era": "modern", "meaning": "happy, joyful"},
    {"value": "瑜", "weight": 0.5, "tags": ["precious", "jade"], "era": "modern", "meaning": "precious jade"},
    {"value": "晴", "weight": 0.5, "tags": ["sunny", "clear"], "era": "modern", "meaning": "sunny, clear"},
    {"value": "蓉", "weight": 0.5, "tags": ["flower", "lotus"], "era": "classic", "meaning": "lotus"},
    {"value": "姿", "weight": 0.5, "tags": ["posture", "graceful"], "era": "classic", "meaning": "graceful posture"},
    {"value": "涵", "weight": 0.4, "tags": ["cultivated", "inclusive"], "era": "modern", "meaning": "cultivated, inclusive"},
    {"value": "詩", "weight": 0.4, "tags": ["literary", "poetic"], "era": "modern", "meaning": "poetry"},
    {"value": "語", "weight": 0.4, "tags": ["communication", "speech"], "era": "modern", "meaning": "speech, language"},
    {"value": "茹", "weight": 0.4, "tags": ["gentle", "soft"], "era": "classic", "meaning": "gentle, soft"},
    {"value": "娟", "weight": 0.4, "tags": ["beautiful", "graceful"], "era": "classic", "meaning": "beautiful, graceful"},
    {"value": "薇", "weight": 0.3, "tags": ["flower", "rose"], "era": "modern", "meaning": "rose"},
    {"value": "瑤", "weight": 0.3, "tags": ["precious", "mythical", "jade"], "era": "classic", "meaning": "precious jade"},
    {"value": "馨", "weight": 0.3, "tags": ["fragrant", "sweet"], "era": "modern", "meaning": "fragrant, sweet"},
    {"value": "妍", "weight": 0.3, "tags": ["beautiful", "lovely"], "era": "modern", "meaning": "beautiful, lovely"},
    {"value": "嫻", "weight": 0.3, "tags": ["elegant", "refined"], "era": "traditional", "meaning": "elegant, refined"},
    {"value": "璇", "weight": 0.3, "tags": ["beautiful", "jade"], "era": "modern", "meaning": "beautiful jade"},
    {"value": "心", "weight": 0.3, "tags": ["pure", "simple", "heart"], "era": "universal", "meaning": "heart, mind"}
  ]
}