{
  "language": "en",
  "country": "US",
  "type": "names",
  "version": "2.0.0",
  "items": [
    {"value": "Smith", "weight": 2.0, "tags": ["occupational", "metalworker"], "origin": "English", "type": "occupational", "meaning": "metalworker"},
    {"value": "Johnson", "weight": 1.8, "tags": ["patronymic", "son"], "origin": "English", "type": "patronymic", "meaning": "son of John"},
    {"value": "Williams", "weight": 1.6, "tags": ["patronymic", "son"], "origin": "English", "type": "patronymic", "meaning": "son of William"},
    {"value": "Brown", "weight": 1.4, "tags": ["descriptive", "color"], "origin": "English", "type": "descriptive", "meaning": "brown-haired or complexioned"},
    {"value": "Jones", "weight": 1.3, "tags": ["patronymic", "son"], "origin": "English", "type": "patronymic", "meaning": "son of John"},
    {"value": "Garcia", "weight": 1.2, "tags": ["spanish", "bear"], "origin": "Spanish", "type": "descriptive", "meaning": "bear"},
    {"value": "Miller", "weight": 1.1, "tags": ["occupational", "grain"], "origin": "English", "type": "occupational", "meaning": "grain miller"},
    {"value": "Davis", "weight": 1.0, "tags": ["patronymic", "son"], "origin": "Welsh", "type": "patronymic", "meaning": "son of David"},
    {"value": "Rodriguez", "weight": 1.0, "tags": ["spanish", "patronymic"], "origin": "Spanish", "type": "patronymic", "meaning": "son of Rodrigo"},
    {"value": "Martinez", "weight": 1.0, "tags": ["spanish", "patronymic"], "origin": "Spanish", "type": "patronymic", "meaning": "son of Martin"},
    {"value": "Hernandez", "weight": 0.9, "tags": ["spanish", "patronymic"], "origin": "Spanish", "type": "patronymic", "meaning": "son of Hernando"},
    {"value": "Lopez", "weight": 0.9, "tags": ["spanish", "patronymic"], "origin": "Spanish", "type": "patronymic", "meaning": "son of Lope"},
    {"value": "Gonzalez", "weight": 0.9, "tags": ["spanish", "patronymic"], "origin": "Spanish", "type": "patronymic", "meaning": "son of Gonzalo"},
    {"value": "Wilson", "weight": 0.8, "tags": ["patronymic", "son"], "origin": "English", "type": "patronymic", "meaning": "son of Will"},
    {"value": "Anderson", "weight": 0.8, "tags": ["scandinavian", "patronymic"], "origin": "Scandinavian", "type": "patronymic", "meaning": "son of Anders"},
    {"value": "Thomas", "weight": 0.8, "tags": ["patronymic", "twin"], "origin": "Aramaic", "type": "patronymic", "meaning": "twin"},
    {"value": "Taylor", "weight": 0.7, "tags": ["occupational", "tailor"], "origin": "English", "type": "occupational", "meaning": "tailor"},
    {"value": "Moore", "weight": 0.7, "tags": ["topographic", "moor"], "origin": "English", "type": "topographic", "meaning": "dweller by the moor"},
    {"value": "Jackson", "weight": 0.7, "tags": ["patronymic", "son"], "origin": "English", "type": "patronymic", "meaning": "son of Jack"},
    {"value": "Martin", "weight": 0.7, "tags": ["roman", "war"], "origin": "Latin", "type": "personal", "meaning": "of Mars, warlike"},
    {"value": "Lee", "weight": 0.6, "tags": ["topographic", "meadow"], "origin": "English", "type": "topographic", "meaning": "meadow"},
    {"value": "Perez", "weight": 0.6, "tags": ["spanish", "patronymic"], "origin": "Spanish", "type": "patronymic", "meaning": "son of Pedro"},
    {"value": "Thompson", "weight": 0.6, "tags": ["patronymic", "son"], "origin": "English", "type": "patronymic", "meaning": "son of Thomas"},
    {"value": "White", "weight": 0.6, "tags": ["descriptive", "color"], "origin": "English", "type": "descriptive", "meaning": "white-haired or pale"},
    {"value": "Harris", "weight": 0.6, "tags": ["patronymic", "son"], "origin": "English", "type": "patronymic", "meaning": "son of Harry"},
    {"value": "Sanchez", "weight": 0.5, "tags": ["spanish", "patronymic"], "origin": "Spanish", "type": "patronymic", "meaning": "son of Sancho"},
    {"value": "Clark", "weight": 0.5, "tags": ["occupational", "clerk"], "origin": "English", "type": "occupational", "meaning": "clerk, scholar"},
    {"value": "Ramirez", "weight": 0.5, "tags": ["spanish", "patronymic"], "origin": "Spanish", "type": "patronymic", "meaning": "son of Ramiro"},
    {"value": "Lewis", "weight": 0.5, "tags": ["germanic", "famous"], "origin": "Germanic", "type": "personal", "meaning": "famous warrior"},
    {"value": "Robinson", "weight": 0.5, "tags": ["patronymic", "son"], "origin": "English", "type": "patronymic", "meaning": "son of Robin"},
    {"value": "Walker", "weight": 0.5, "tags": ["occupational", "cloth"], "origin": "English", "type": "occupational", "meaning": "cloth walker"},
    {"value": "Young", "weight": 0.4, "tags": ["descriptive", "age"], "origin": "English", "type": "descriptive", "meaning": "young"},
    {"value": "Allen", "weight": 0.4, "tags": ["celtic", "handsome"], "origin": "Celtic", "type": "personal", "meaning": "handsome, cheerful"},
    {"value": "King", "weight": 0.4, "tags": ["occupational", "royal"], "origin": "English", "type": "occupational", "meaning": "king, ruler"},
    {"value": "Wright", "weight": 0.4, "tags": ["occupational", "craftsman"], "origin": "English", "type": "occupational", "meaning": "craftsman, maker"},
    {"value": "Scott", "weight": 0.4, "tags": ["ethnic", "scottish"], "origin": "English", "type": "ethnic", "meaning": "from Scotland"},
    {"value": "Torres", "weight": 0.4, "tags": ["spanish", "towers"], "origin": "Spanish", "type": "topographic", "meaning": "towers"},
    {"value": "Nguyen", "weight": 0.4, "tags": ["vietnamese", "royal"], "origin": "Vietnamese", "type": "personal", "meaning": "musical instrument"},
    {"value": "Hill", "weight": 0.4, "tags": ["topographic", "hill"], "origin": "English", "type": "topographic", "meaning": "dweller by the hill"},
    {"value": "Flores", "weight": 0.3, "tags": ["spanish", "flowers"], "origin": "Spanish", "type": "topographic", "meaning": "flowers"},
    {"value": "Green", "weight": 0.3, "tags": ["descriptive", "color"], "origin": "English", "type": "topographic", "meaning": "green, village green"},
    {"value": "Adams", "weight": 0.3, "tags": ["patronymic", "son"], "origin": "English", "type": "patronymic", "meaning": "son of Adam"},
    {"value": "Nelson", "weight": 0.3, "tags": ["patronymic", "son"], "origin": "English", "type": "patronymic", "meaning": "son of Neil"},
    {"value": "Baker", "weight": 0.3, "tags": ["occupational", "bread"], "origin": "English", "type": "occupational", "meaning": "baker"},
    {"value": "Hall", "weight": 0.3, "tags": ["topographic", "hall"], "origin": "English", "type": "topographic", "meaning": "dweller by the hall"},
    {"value": "Rivera", "weight": 0.3, "tags": ["spanish", "river"], "origin": "Spanish", "type": "topographic", "meaning": "riverbank"},
    {"value": "Campbell", "weight": 0.3, "tags": ["scottish", "crooked"], "origin": "Scottish", "type": "descriptive", "meaning": "crooked mouth"},
    {"value": "Mitchell", "weight": 0.3, "tags": ["patronymic", "son"], "origin": "English", "type": "patronymic", "meaning": "son of Michael"},
    {"value": "Carter", "weight": 0.3, "tags": ["occupational", "cart"], "origin": "English", "type": "occupational", "meaning": "cart driver"},
    {"value": "Roberts", "weight": 0.3, "tags": ["patronymic", "son"], "origin": "English", "type": "patronymic", "meaning": "son of Robert"}
  ]
}